agora_graphql/__init__.py
agora_graphql/metadata.json
agora_graphql/gql/__init__.py
agora_graphql/gql/data.py
agora_graphql/gql/executor.py
agora_graphql/gql/middleware.py
agora_graphql/gql/schema.py
agora_graphql/gql/sparql.py
agora_graphql/misc/__init__.py
agora_graphql/server/__init__.py
agora_graphql/server/app.py
agora_graphql/server/view.py
agora_graphql-0.1.10.data/scripts/gql
agora_graphql-0.1.10.dist-info/LICENSE
agora_graphql-0.1.10.dist-info/METADATA
agora_graphql-0.1.10.dist-info/WHEEL
agora_graphql-0.1.10.dist-info/top_level.txt
agora_graphql-0.1.10.dist-info/RECORD
